chaosinjector/__init__.py
chaosinjector/base.py
chaosinjector-0.3.0.dist-info/METADATA
chaosinjector-0.3.0.dist-info/WHEEL
chaosinjector-0.3.0.dist-info/licenses/LICENSE
chaosinjector-0.3.0.dist-info/RECORD
