Metadata-Version: 2.4
Name: chaosinjector
Version: 0.3.0
Summary: ChaosInjector: Probabilistic proxy library for injecting randomness and faults into Python objects. Supports chaos engineering, fault injection, stochastic simulations, A/B testing, and data privacy masking with type preservation.
Project-URL: Homepage, https://github.com/vproyaev/chaosinjector
Project-URL: Issues, https://github.com/vproyaev/chaosinjector/issues
Project-URL: Documentation, https://chaosinjector.readthedocs.io
Author-email: Vladislav Proyaev <farmfilok@gmail.com>
License: MIT License
License-File: LICENSE
Keywords: A/B testing python,chaos engineering,data anonymization,fault injection,monte carlo python,performance sampling,probabilistic proxy,python testing library,randomness injection,stochastic simulation
Classifier: License :: OSI Approved :: MIT License
Classifier: Operating System :: OS Independent
Classifier: Programming Language :: Python :: 3
Requires-Python: >=3.8
Provides-Extra: dev
Requires-Dist: pytest; extra == 'dev'
